{"surah":"54", "verses": [{"verse_key":"54:1","id":4847,"text":"اِقۡتَـرَبَتِ السَّاعَةُ وَانْشَقَّ الۡقَمَرُ\u200F"},
{"verse_key":"54:2","id":4848,"text":"وَاِنۡ يَّرَوۡا اٰيَةً يُّعۡرِضُوۡا وَيَقُوۡلُوۡا سِحۡرٌ مُّسۡتَمِرٌّ\u200F"},
{"verse_key":"54:3","id":4849,"text":"وَكَذَّبُوۡا وَاتَّبَعُوۡۤا اَهۡوَآءَهُمۡ\u200B وَكُلُّ اَمۡرٍ مُّسۡتَقِرٌّ\u200F"},
{"verse_key":"54:4","id":4850,"text":"وَلَقَدۡ جَآءَهُمۡ مِّنَ الۡاَنۡۢبَآءِ مَا فِيۡهِ مُزۡدَجَرٌۙ\u200F"},
{"verse_key":"54:5","id":4851,"text":"حِكۡمَةٌ ۢ بَالِغَةٌ\u200B فَمَا تُغۡنِ النُّذُرُۙ\u200F"},
{"verse_key":"54:6","id":4852,"text":"فَتَوَلَّ عَنۡهُمۡ\u200Bۘ يَوۡمَ يَدۡعُ الدَّاعِ اِلٰى شَىۡءٍ نُّكُرٍۙ\u200F"},
{"verse_key":"54:7","id":4853,"text":"خُشَّعًا اَبۡصَارُهُمۡ يَخۡرُجُوۡنَ مِنَ الۡاَجۡدَاثِ كَاَنَّهُمۡ جَرَادٌ مُّنۡتَشِرٌۙ\u200F"},
{"verse_key":"54:8","id":4854,"text":"مُّهۡطِعِيۡنَ اِلَى الدَّاعِ\u200Bؕ يَقُوۡلُ الۡكٰفِرُوۡنَ هٰذَا يَوۡمٌ عَسِرٌ\u200F ﻿﻿"},
{"verse_key":"54:9","id":4855,"text":"كَذَّبَتۡ قَبۡلَهُمۡ قَوۡمُ نُوۡحٍ فَكَذَّبُوۡا عَبۡدَنَا وَقَالُوۡا مَجۡنُوۡنٌ وَّازۡدُجِرَ\u200F"},
{"verse_key":"54:10","id":4856,"text":"فَدَعَا رَبَّهٗۤ اَنِّىۡ مَغۡلُوۡبٌ فَانْـتَصِرۡ\u200F"},
{"verse_key":"54:11","id":4857,"text":"فَفَتَحۡنَاۤ اَبۡوَابَ السَّمَآءِ بِمَآءٍ مُّنۡهَمِرٍ\u2002ۖ\u200F"},
{"verse_key":"54:12","id":4858,"text":"وَّفَجَّرۡنَا الۡاَرۡضَ عُيُوۡنًا فَالۡتَقَى الۡمَآءُ عَلٰٓى اَمۡرٍ قَدۡ قُدِرَ\u200Bۚ\u200F"},
{"verse_key":"54:13","id":4859,"text":"وَحَمَلۡنٰهُ عَلٰى ذَاتِ اَلۡوَاحٍ وَّدُسُرٍۙ\u200F"},
{"verse_key":"54:14","id":4860,"text":"تَجۡرِىۡ بِاَعۡيُنِنَا\u200Bۚ جَزَآءً لِّمَنۡ كَانَ كُفِرَ\u200F"},
{"verse_key":"54:15","id":4861,"text":"وَلَقَدْ تَّرَكۡنٰهَاۤ اٰيَةً فَهَلۡ مِنۡ مُّدَّكِرٍ\u200F"},
{"verse_key":"54:16","id":4862,"text":"فَكَيۡفَ كَانَ عَذَابِىۡ وَنُذُرِ\u200F"},
{"verse_key":"54:17","id":4863,"text":"وَلَقَدۡ يَسَّرۡنَا الۡقُرۡاٰنَ لِلذِّكۡرِ فَهَلۡ مِنۡ مُّدَّكِرٍ\u200F"},
{"verse_key":"54:18","id":4864,"text":"كَذَّبَتۡ عَادٌ فَكَيۡفَ كَانَ عَذَابِىۡ وَنُذُرِ\u200F"},
{"verse_key":"54:19","id":4865,"text":"اِنَّاۤ اَرۡسَلۡنَا عَلَيۡهِمۡ رِيۡحًا صَرۡصَرًا فِىۡ يَوۡمِ نَحۡسٍ مُّسۡتَمِرٍّۙ\u200F ﻿﻿"},
{"verse_key":"54:20","id":4866,"text":"تَنۡزِعُ النَّاسَۙ كَاَنَّهُمۡ اَعۡجَازُ نَخۡلٍ مُّنۡقَعِرٍ\u200F"},
{"verse_key":"54:21","id":4867,"text":"فَكَيۡفَ كَانَ عَذَابِىۡ وَنُذُرِ\u200F"},
{"verse_key":"54:22","id":4868,"text":"وَلَقَدۡ يَسَّرۡنَا الۡقُرۡاٰنَ لِلذِّكۡرِ فَهَلۡ مِنۡ مُّدَّكِرٍ\u200F"},
{"verse_key":"54:23","id":4869,"text":"كَذَّبَتۡ ثَمُوۡدُ بِالنُّذُرِ\u200F"},
{"verse_key":"54:24","id":4870,"text":"فَقَالُـوۡۤا اَبَشَرًا مِّنَّا وَاحِدًا نَّتَّبِعُهٗۤ ۙ اِنَّاۤ اِذًا لَّفِىۡ ضَلٰلٍ وَّسُعُرٍ\u200F"},
{"verse_key":"54:25","id":4871,"text":"ءَاُلۡقِىَ الذِّكۡرُ عَلَيۡهِ مِنۡۢ بَيۡنِنَا بَلۡ هُوَ كَذَّابٌ اَشِرٌ\u200F"},
{"verse_key":"54:26","id":4872,"text":"سَيَعۡلَمُوۡنَ غَدًا مَّنِ الۡكَذَّابُ الۡاَشِرُ\u200F"},
{"verse_key":"54:27","id":4873,"text":"اِنَّا مُرۡسِلُوا النَّاقَةِ فِتۡنَةً لَّهُمۡ فَارۡتَقِبۡهُمۡ وَاصۡطَبِرۡ\u200F ﻿﻿"},
{"verse_key":"54:28","id":4874,"text":"وَنَبِّئۡهُمۡ اَنَّ الۡمَآءَ قِسۡمَةٌ ۢ بَيۡنَهُمۡ\u200Bۚ كُلُّ شِرۡبٍ مُّحۡتَضَرٌ\u200F ﻿﻿"},
{"verse_key":"54:29","id":4875,"text":"فَنَادَوۡا صَاحِبَهُمۡ فَتَعَاطٰى فَعَقَرَ\u200F"},
{"verse_key":"54:30","id":4876,"text":"فَكَيۡفَ كَانَ عَذَابِىۡ وَنُذُرِ\u200F"},
{"verse_key":"54:31","id":4877,"text":"اِنَّاۤ اَرۡسَلۡنَا عَلَيۡهِمۡ صَيۡحَةً وَّاحِدَةً فَكَانُوۡا كَهَشِيۡمِ الۡمُحۡتَظِرِ\u200F ﻿﻿"},
{"verse_key":"54:32","id":4878,"text":"وَلَقَدۡ يَسَّرۡنَا الۡقُرۡاٰنَ لِلذِّكۡرِ فَهَلۡ مِنۡ مُّدَّكِرٍ\u200F"},
{"verse_key":"54:33","id":4879,"text":"كَذَّبَتۡ قَوۡمُ لُوۡطٍ ۢ بِالنُّذُرِ\u200F"},
{"verse_key":"54:34","id":4880,"text":"اِنَّاۤ اَرۡسَلۡنَا عَلَيۡهِمۡ حَاصِبًا اِلَّاۤ اٰلَ لُوۡطٍ\u200Bؕ نَّجَّيۡنٰهُمۡ بِسَحَرٍۙ\u200F"},
{"verse_key":"54:35","id":4881,"text":"نِّعۡمَةً مِّنۡ عِنۡدِنَا\u200Bؕ كَذٰلِكَ نَجۡزِىۡ مَنۡ شَكَرَ\u200F"},
{"verse_key":"54:36","id":4882,"text":"وَلَقَدۡ اَنۡذَرَهُمۡ بَطۡشَتَـنَا فَتَمَارَوۡا بِالنُّذُرِ\u200F"},
{"verse_key":"54:37","id":4883,"text":"وَلَقَدۡ رَاوَدُوۡهُ عَنۡ ضَيۡفِهٖ فَطَمَسۡنَاۤ اَعۡيُنَهُمۡ فَذُوۡقُوۡا عَذَابِىۡ وَنُذُرِ\u200F"},
{"verse_key":"54:38","id":4884,"text":"وَلَقَدۡ صَبَّحَهُمۡ بُكۡرَةً عَذَابٌ مُّسۡتَقِرٌّ\u200B\u2002ۚ\u200F"},
{"verse_key":"54:39","id":4885,"text":"فَذُوۡقُوۡا عَذَابِىۡ وَنُذُرِ\u200F"},
{"verse_key":"54:40","id":4886,"text":"وَلَقَدۡ يَسَّرۡنَا الۡقُرۡاٰنَ لِلذِّكۡرِ فَهَلۡ مِنۡ مُّدَّكِرٍ\u200F"},
{"verse_key":"54:41","id":4887,"text":"وَلَقَدۡ جَآءَ اٰلَ فِرۡعَوۡنَ النُّذُرُ\u200Bۚ\u200F"},
{"verse_key":"54:42","id":4888,"text":"كَذَّبُوۡا بِاٰيٰتِنَا كُلِّهَا فَاَخَذۡنٰهُمۡ اَخۡذَ عَزِيۡزٍ مُّقۡتَدِرٍ\u200F ﻿﻿"},
{"verse_key":"54:43","id":4889,"text":"اَكُفَّارُكُمۡ خَيۡرٌ مِّنۡ اُولٰٓٮِٕكُمۡ اَمۡ لَكُمۡ بَرَآءَةٌ فِى الزُّبُرِ\u200Bۚ\u200F ﻿﻿"},
{"verse_key":"54:44","id":4890,"text":"اَمۡ يَقُوۡلُوۡنَ نَحۡنُ جَمِيۡعٌ مُّنۡتَصِرٌ\u200F"},
{"verse_key":"54:45","id":4891,"text":"سَيُهۡزَمُ الۡجَمۡعُ وَيُوَلُّوۡنَ الدُّبُرَ\u200F"},
{"verse_key":"54:46","id":4892,"text":"بَلِ السَّاعَةُ مَوۡعِدُهُمۡ وَالسَّاعَةُ اَدۡهٰى وَاَمَرُّ\u200F"},
{"verse_key":"54:47","id":4893,"text":"اِنَّ الۡمُجۡرِمِيۡنَ فِىۡ ضَلٰلٍ وَّسُعُرٍ\u200Bۘ\u200F"},
{"verse_key":"54:48","id":4894,"text":"يَوۡمَ يُسۡحَبُوۡنَ فِى النَّارِ عَلٰى وُجُوۡهِهِمۡؕ ذُوۡقُوۡا مَسَّ سَقَرَ\u200F ﻿﻿"},
{"verse_key":"54:49","id":4895,"text":"اِنَّا كُلَّ شَىۡءٍ خَلَقۡنٰهُ بِقَدَرٍ\u200F"},
{"verse_key":"54:50","id":4896,"text":"وَمَاۤ اَمۡرُنَاۤ اِلَّا وَاحِدَةٌ كَلَمۡحٍۢ بِالۡبَصَرِ\u200F"},
{"verse_key":"54:51","id":4897,"text":"وَلَقَدۡ اَهۡلَـكۡنَاۤ اَشۡيَاعَكُمۡ فَهَلۡ مِنۡ مُّدَّكِرٍ\u200F"},
{"verse_key":"54:52","id":4898,"text":"وَكُلُّ شَىۡءٍ فَعَلُوۡهُ فِى الزُّبُرِ\u200F"},
{"verse_key":"54:53","id":4899,"text":"وَ كُلُّ صَغِيۡرٍ وَّكَبِيۡرٍ مُّسۡتَطَرٌ\u200F"},
{"verse_key":"54:54","id":4900,"text":"اِنَّ الۡمُتَّقِيۡنَ فِىۡ جَنّٰتٍ وَّنَهَرٍۙ\u200F"},
{"verse_key":"54:55","id":4901,"text":"\u2003\u2003فِىۡ مَقۡعَدِ صِدۡقٍ عِنۡدَ مَلِيۡكٍ مُّقۡتَدِرٍ\u200F"}]}